ghuc.py
ghuc-0.1.dist-info/COPYING
ghuc-0.1.dist-info/METADATA
ghuc-0.1.dist-info/WHEEL
ghuc-0.1.dist-info/entry_points.txt
ghuc-0.1.dist-info/top_level.txt
ghuc-0.1.dist-info/RECORD
