Metadata-Version: 2.1
Name: ghuc
Version: 0.1
Summary: Upload images/documents to GitHub as issue attachments
Home-page: https://github.com/zmwangx/ghuc
Author: Zhiming Wang
Author-email: i@zhimingwang.org
License: MIT
Keywords: github image upload headless browser
Platform: UNKNOWN
Classifier: Development Status :: 4 - Beta
Classifier: Environment :: Console
Classifier: Intended Audience :: Developers
Classifier: License :: OSI Approved :: MIT License
Classifier: Operating System :: OS Independent
Classifier: Programming Language :: Python
Classifier: Programming Language :: Python :: 3
Classifier: Programming Language :: Python :: 3.5
Classifier: Programming Language :: Python :: 3.6
Classifier: Programming Language :: Python :: 3.7
Classifier: Programming Language :: Python :: 3 :: Only
Classifier: Programming Language :: Python :: Implementation :: CPython
Classifier: Topic :: Internet
Classifier: Topic :: Multimedia
Classifier: Topic :: Utilities
Requires-Python: >=3.4
Requires-Dist: pyotp
Requires-Dist: python-magic
Requires-Dist: selenium
Requires-Dist: urllib3[secure,socks]
Requires-Dist: xdgappdirs (>=1.4.5)
Provides-Extra: test
Requires-Dist: Pillow ; extra == 'test'
Requires-Dist: pytest ; extra == 'test'
